[
  {
    "question": "You meet a friend on the way to school. What do you say?",
    "answerOptions": [
      { "answer": "Good night" },
      { "answer": "Nice to meet you" },
      { "answer": "Good bye" },
      { "answer": "Good morning", "isCorrect": true }
    ]
  },
  {
    "question": "Dena: Hi, Andi. How are you?\nBayu: I am fine, thank you.\nDena: I'd like you to meet Gede. Gede, this is Bayu.\nGede: Hello, I am Gede. _______\nBayu: Nice to meet you, too.\n",
    "answerOptions": [
      { "answer": "I am well, thank you" },
      { "answer": "good meet morning" },
      { "answer": "how do you do?" },
      { "answer": "nice to meet you", "isCorrect": true }
    ]
  },
  {
    "question": "Anisa: Excuse me, Are you Mutiara?\nMutiara: Yes, that's me.\nAnisa: I'm glad I finally got to meet you in person. How do you do, Mutiara?\nMutiara: How do you do?\nFrom the dialog above, Anisa is…",
    "answerOptions": [
      { "answer": "helping Mutiara" },
      { "answer": "greeting Mutiara", "isCorrect": true },
      { "answer": "apologizing to Mutiara" },
      { "answer": "thanking Mutiara" }
    ]
  },
  {
    "question": "Sasa: Hi Indah. Long time no see\nIndah: Hi Sasa. Long time no see. How are you?\nSasa: I'm fine. How about you?\nIndah: I'm fine too.\nWhich expressions show greetings?",
    "answerOptions": [
      { "answer": "How are you?", "isCorrect": true },
      { "answer": "See you later" },
      { "answer": "Long time no see" },
      { "answer": "I`m sorry" }
    ]
  },
  {
    "question": "Sandra: Hi, Noah. I didn't expect to meet you in piano course\nNoah: Hello, Sandra. Yes, I just joined last week. How are you, Sandra?\nSandra: I`m very good.\nFrom the dialogue above it can be concluded that....",
    "answerOptions": [
      { "answer": "Noah and Sandra learn piano together" },
      { "answer": "Sandra moves to piano course last week" },
      { "answer": "Sandra greets Noah first when they meet in piano course", "isCorrect": true },
      { "answer": "Noah is Sandra`s old friend" }
    ]
  }
]
